MANIFEST.in
README.rst
setup.py
starling/__init__.py
starling/time_point.py
starling.egg-info/PKG-INFO
starling.egg-info/SOURCES.txt
starling.egg-info/dependency_links.txt
starling.egg-info/requires.txt
starling.egg-info/top_level.txt
starling.egg-info/zip-safe
starling/flask/__init__.py
starling/flask/template_filter.py
starling/flask/error_handler/__init__.py
starling/flask/error_handler/error_code.py
starling/flask/error_handler/json.py
starling/pika/__init__.py
starling/pika/decorator.py